bapp_store/__main__.py
bapp_store-2.0.0.dist-info/LICENSE
bapp_store-2.0.0.dist-info/METADATA
bapp_store-2.0.0.dist-info/WHEEL
bapp_store-2.0.0.dist-info/entry_points.txt
bapp_store-2.0.0.dist-info/RECORD
