Metadata-Version: 2.1
Name: bapp-store
Version: 2.0.0
Summary: A simple app store for Beepy applications
Home-page: https://github.com/conor-f/bapp-store
License: GPL-3.0-only
Author: Conor Flynn
Author-email: beepy@randombits.host
Requires-Python: >=3.8,<4.0
Classifier: Development Status :: 3 - Alpha
Classifier: Intended Audience :: Developers
Classifier: License :: OSI Approved :: GNU General Public License v3 (GPLv3)
Classifier: Programming Language :: Python :: 3
Classifier: Programming Language :: Python :: 3.8
Classifier: Programming Language :: Python :: 3.9
Classifier: Programming Language :: Python :: 3.10
Classifier: Programming Language :: Python :: 3.11
Classifier: Programming Language :: Python :: 3.12
Classifier: Programming Language :: Python :: 3.13
Requires-Dist: requests (>=2.31.0,<3.0.0)
Requires-Dist: rich (>=13.5.2,<14.0.0)
Requires-Dist: textual (>=0.10.1,<0.11.0)
